email_users/__init__.py
email_users/admin.py
email_users/apps.py
email_users/models.py
email_users/tests.py
email_users/migrations/0001_initial.py
email_users/migrations/0002_group.py
email_users/migrations/__init__.py
django_cust_email_user-0.1.2.dist-info/METADATA
django_cust_email_user-0.1.2.dist-info/WHEEL
django_cust_email_user-0.1.2.dist-info/top_level.txt
django_cust_email_user-0.1.2.dist-info/RECORD
