Metadata-Version: 2.1
Name: django-cust-email-user
Version: 0.1.2
Summary: Just another Django-email-user app. Makes the email address as the username.
Home-page: https://github.com/red-pepper-services/django-emailuser
Author: red-pepper-services
Author-email: pypi@schiegg.at
License: MIT
Classifier: Development Status :: 3 - Alpha
Classifier: Framework :: Django
Classifier: Intended Audience :: Developers
Classifier: License :: OSI Approved :: MIT License
Classifier: Operating System :: OS Independent
Classifier: Programming Language :: Python
